dbsettings/__init__.py
dbsettings/admin.py
dbsettings/apps.py
dbsettings/functions.py
dbsettings/models.py
dbsettings/views.py
dbsettings/migrations/0001_initial.py
dbsettings/migrations/0002_setting_description.py
dbsettings/migrations/__init__.py
dbsettings/templatetags/__init__.py
dbsettings/templatetags/dbsetting.py
dbsettings-0.9.8.dist-info/licenses/LICENSE
dbsettings-0.9.8.dist-info/METADATA
dbsettings-0.9.8.dist-info/WHEEL
dbsettings-0.9.8.dist-info/top_level.txt
dbsettings-0.9.8.dist-info/RECORD
