Metadata-Version: 2.4
Name: dbsettings
Version: 0.9.8
Summary: A Django app to store key-value pairs in the database
Author-email: Kumi <dbsettings@kumi.email>
Project-URL: Homepage, https://git.private.coffee/kumi/django-dbsettings
Project-URL: Bug Tracker, https://git.private.coffee/kumi/django-dbsettings/issues
Project-URL: Source Code, https://git.private.coffee/kumi/django-dbsettings
Classifier: Environment :: Web Environment
Classifier: Framework :: Django
Classifier: Framework :: Django :: 3.0
Classifier: Intended Audience :: Developers
Classifier: License :: OSI Approved :: BSD License
Classifier: Operating System :: OS Independent
Classifier: Programming Language :: Python
Classifier: Programming Language :: Python :: 3
Classifier: Programming Language :: Python :: 3 :: Only
Classifier: Programming Language :: Python :: 3.6
Classifier: Programming Language :: Python :: 3.7
Classifier: Programming Language :: Python :: 3.8
Classifier: Programming Language :: Python :: 3.9
Classifier: Programming Language :: Python :: 3.10
Classifier: Programming Language :: Python :: 3.11
Classifier: Programming Language :: Python :: 3.12
Classifier: Programming Language :: Python :: 3.13
Classifier: Topic :: Internet :: WWW/HTTP
Classifier: Topic :: Internet :: WWW/HTTP :: Dynamic Content
Requires-Python: >=3.6
License-File: LICENSE
Requires-Dist: django
Dynamic: license-file
